MANIFEST.in
Makefile
README
mangler.py
setup.py
tiddlywebconfig.py
src/common/test1.tid
src/common/test2.js.js
test/__init__.py
test/__init__.pyc
test/test_basic.py
test/__pycache__/test_basic.cpython-27-PYTEST.pyc
tiddlywebplugins/__init__.py
tiddlywebplugins/devstore2.py
tiddlywebplugins.devstore2.egg-info/PKG-INFO
tiddlywebplugins.devstore2.egg-info/SOURCES.txt
tiddlywebplugins.devstore2.egg-info/dependency_links.txt
tiddlywebplugins.devstore2.egg-info/namespace_packages.txt
tiddlywebplugins.devstore2.egg-info/not-zip-safe
tiddlywebplugins.devstore2.egg-info/requires.txt
tiddlywebplugins.devstore2.egg-info/top_level.txt