Metadata-Version: 1.0
Name: tiddlywebplugins.devstore2
Version: 0.3
Summary: Development oriented store that wraps another.
Home-page: http://pypi.python.org/pypi/tiddlywebplugins.devstore2
Author: Chris Dent
Author-email: cdent@peermore.com
License: UNKNOWN
Platform: Posix; MacOS X; Windows
